dslib/__init__.py
dslib/gcs_utils.py
dslib_wayfair-0.1.1.dist-info/METADATA
dslib_wayfair-0.1.1.dist-info/WHEEL
dslib_wayfair-0.1.1.dist-info/top_level.txt
dslib_wayfair-0.1.1.dist-info/RECORD
