Metadata-Version: 2.4
Name: dslib-wayfair
Version: 0.1.1
Summary: A utility library for working data pipelines
Home-page: https://github.com/wayfair-sandbox/dslib
Author: Raj Jha
Author-email: rjha4@wayfair.com
Classifier: Programming Language :: Python :: 3
Dynamic: author
Dynamic: author-email
Dynamic: classifier
Dynamic: home-page
Dynamic: summary
